weylchamber/__init__.py
weylchamber/_types.py
weylchamber/coordinates.py
weylchamber/gates.py
weylchamber/local_invariants.py
weylchamber/perfect_entanglers.py
weylchamber/prec.py
weylchamber/visualize.py
weylchamber-0.6.0.dist-info/AUTHORS.rst
weylchamber-0.6.0.dist-info/LICENSE
weylchamber-0.6.0.dist-info/METADATA
weylchamber-0.6.0.dist-info/WHEEL
weylchamber-0.6.0.dist-info/top_level.txt
weylchamber-0.6.0.dist-info/RECORD
