Metadata-Version: 2.1
Name: weylchamber
Version: 0.6.0
Summary: Python package for analyzing two-qubit gates in the Weyl chamber
Home-page: https://github.com/qucontrol/weylchamber
Author: Michael Goerz
Author-email: mail@michaelgoerz.net
License: BSD license
Keywords: weylchamber
Classifier: Development Status :: 3 - Alpha
Classifier: Intended Audience :: Science/Research
Classifier: License :: OSI Approved :: BSD License
Classifier: Natural Language :: English
Classifier: Programming Language :: Python :: 3.8
Classifier: Programming Language :: Python :: 3.9
License-File: LICENSE
License-File: AUTHORS.rst
Requires-Dist: numpy <2.0
Requires-Dist: scipy
Requires-Dist: matplotlib >=3.3.0
Requires-Dist: qutip >=5.0
Provides-Extra: dev
Requires-Dist: better-apidoc ==0.3.2 ; extra == 'dev'
Requires-Dist: click ; extra == 'dev'
Requires-Dist: coverage ; extra == 'dev'
Requires-Dist: flake8 ; extra == 'dev'
Requires-Dist: gitpython ; extra == 'dev'
Requires-Dist: jupyter ; extra == 'dev'
Requires-Dist: nbsphinx ; extra == 'dev'
Requires-Dist: nbval ; extra == 'dev'
Requires-Dist: pep8 ; extra == 'dev'
Requires-Dist: pytest ; extra == 'dev'
Requires-Dist: pytest-cov ; extra == 'dev'
Requires-Dist: pytest-xdist ; extra == 'dev'
Requires-Dist: sphinx ; extra == 'dev'
Requires-Dist: sphinx-autobuild ; extra == 'dev'
Requires-Dist: sphinx-autodoc-typehints ; extra == 'dev'
Requires-Dist: sphinx-rtd-theme ==2.0.0 ; extra == 'dev'
Requires-Dist: docs-versions-menu ; extra == 'dev'
Requires-Dist: twine ; extra == 'dev'
Requires-Dist: watermark ; extra == 'dev'
Requires-Dist: wheel ; extra == 'dev'
